dexsim/__init__.py
dexsim/dex.py
dexsim/lender.py
dexsim/lp.py
dexsim/pool.py
dexsim/snapshot.py
dexsim/utils.py
dexsim/abis/Lender.json
dexsim/abis/NonFungPosition.abi
dexsim/abis/PoolToken.json
dexsim/abis/Quoterv2.abi
dexsim/abis/Quoterv2.bin
dexsim/abis/SwapRouter.abi
dexsim/abis/UniswapV3Factory.abi
dexsim/abis/UniswapV3Pool.abi
dexsim/abis/__init__.py
dexsim/state/base.json
dexsim/state/pairs.yaml
dexsim/state/pool_snapshot.json
dexsim/state/quoter_pool_snapshot.json
dexsim/state/tokens.yaml
dexsim-0.2.3.dist-info/METADATA
dexsim-0.2.3.dist-info/WHEEL
dexsim-0.2.3.dist-info/licenses/LICENSE
dexsim-0.2.3.dist-info/RECORD
