Metadata-Version: 2.3
Name: dexsim
Version: 0.2.3
Summary: API to create and interact with a Uniswap based decentralized exchange
Author-email: Dave Bryson <davebryson@users.noreply.github.com>
License: Apache-2.0
Keywords: agent-based modeling,ethereum,simulation,solidity,uniswap
Classifier: Development Status :: 4 - Beta
Classifier: Programming Language :: Python
Classifier: Programming Language :: Python :: 3.10
Classifier: Programming Language :: Python :: 3.11
Classifier: Programming Language :: Python :: Implementation :: CPython
Classifier: Programming Language :: Python :: Implementation :: PyPy
Requires-Python: <3.12,>=3.10
Requires-Dist: omegaconf
Requires-Dist: simular-evm==0.3.0
